augment/__init__.py
augment/augment.py
augment/transform.py
augment_nd-0.1.3.dist-info/LICENSE
augment_nd-0.1.3.dist-info/METADATA
augment_nd-0.1.3.dist-info/WHEEL
augment_nd-0.1.3.dist-info/top_level.txt
augment_nd-0.1.3.dist-info/RECORD
