Metadata-Version: 2.1
Name: augment-nd
Version: 0.1.3
Summary: Simple elastic augmentation for ND arrays.
Author-email: Jan Funke <funkej@hhmi.org>
License: MIT
Classifier: Programming Language :: Python :: 3
Requires-Python: >=3.7
License-File: LICENSE
Requires-Dist: numpy
Requires-Dist: scipy
Requires-Dist: h5py
Provides-Extra: dev
Requires-Dist: pytest-cov ; extra == 'dev'
Requires-Dist: pytest ; extra == 'dev'
Requires-Dist: black ; extra == 'dev'
Requires-Dist: mypy ; extra == 'dev'
